dashcamcsv/__init__.py
dashcamcsv/core.py
dashcamcsv/plotting.py
dashcamcsv-0.2.5.dist-info/METADATA
dashcamcsv-0.2.5.dist-info/WHEEL
dashcamcsv-0.2.5.dist-info/RECORD
