Metadata-Version: 2.4
Name: dashcamcsv
Version: 0.2.5
Summary: Helpful utilities for data science workflows.
Author-email: Reetu Raj Harsh <reeturaj.harsh@neuralweb.tech>
Requires-Python: >=3.8
Requires-Dist: matplotlib>=3.0.0
Requires-Dist: pandas>=1.0.0
Requires-Dist: seaborn>=0.13.2
